[
{
    "name": "v0.2.0 (latest)",
    "version": "stable",
    "url": "https://corese-stack.github.io/corese-python/v0.2.0/",
    "preferred": true
},
{
    "name": "v0.1.5 (stable)",
    "version": "stable",
    "url": "https://corese-stack.github.io/corese-python/v0.1.5/",
    "preferred": false
},
{
    "name": "v0.0.0 (stable)",
    "version": "stable",
    "url": "https://corese-stack.github.io/corese-python/v0.0.0/",
    "preferred": false
},
{
    "name": "dev",
    "version": "unstable",
    "url": "https://corese-stack.github.io/corese-python/dev/",
    "preferred": false
}
]
